[{"question":"Trong Windows, từ Shortcut có ý nghĩa gì?","level":1,"answer":[{"text":"Tạo đường tắt để truy cập nhanh","isCorrect":true},{"text":"Xóa một đối tượng được chọn tại màn hình nền","isCorrect":false},{"text":"Đóng các cửa sổ đang mở","isCorrect":false},{"text":"Tạo một ứng dụng","isCorrect":false}],"score":0.0},{"question":"Trong Windows, ở cửa sổ Explorer, để chọn một lúc các file hoặc folder nằm không kề nhau:","level":1,"answer":[{"text":"Giữ phím Ctrl và click chuột vào từng mục muốn chọn trong danh sách","isCorrect":true},{"text":"Nháy chuột ở mục đầu, ấn và giữ Shift nháy chuột ở mục cuối","isCorrect":false},{"text":"Giữ phím Alt và nháy chuột vào từng mục muốn chọn trong danh sách","isCorrect":false},{"text":"Giữ phím Tab và nháy chuột vào từng mục muốn chọn trong danh sách","isCorrect":false}],"score":0.0},{"question":"Trong Windows, muốn khôi phục đối tượng đã xóa, mở cửa sổ Recycle Bin và thực hiện thao tác nào sau đây? ","level":1,"answer":[{"text":"Kích chuột phải tại đối tượng, chọn Restore","isCorrect":true},{"text":"Kích chuột phải tại đối tượng, chọn Cut","isCorrect":false},{"text":"Kích chuột phải tại đối tượng, chọn Properties","isCorrect":false},{"text":"Kích chuột phải tại đối tượng, chọn Undo","isCorrect":false}],"score":0.0},{"question":"Trong Windows, khi xoá file hoặc folder thì nó được lưu trong Recycle Bin, muốn xoá hẳn file hoặc folder ta bấm tổ hợp phím nào:","level":1,"answer":[{"text":"Shift+Delete","isCorrect":true},{"text":"Alt+Delete","isCorrect":false},{"text":"Ctrl+Delete","isCorrect":false},{"text":"Fn+ Delete","isCorrect":false}],"score":0.0},{"question":"Trong Windows, để đổi tên thư mục ta thực hiện:","level":1,"answer":[{"text":"Click nút phải chuột tại thư mục -> Rename -> gõ tên mới -> enter","isCorrect":true},{"text":"Click nút phải chuột tại thư mục -> Delete -> gõ tên mới -> enter","isCorrect":false},{"text":"Click nút phải chuột tại thư mục -> New ->gõ tên mới -> enter","isCorrect":false},{"text":"Click nút phải chuột tại thư mục -> File/new/folder -> gõ tên mới -> enter","isCorrect":false}],"score":0.0},{"question":"Trong Windows, click chuột phải vào thư mục và chọn Delete thì:","level":1,"answer":[{"text":"Xóa thư mục vào thùng rác","isCorrect":true},{"text":"Xóa vĩnh viễn thư mục","isCorrect":false},{"text":"Xóa thư mục trong thùng rác","isCorrect":false},{"text":"Xoá tạm thời khi quay lại vẫn còn","isCorrect":false}],"score":0.0},{"question":"Trong Windows, click chuột phải vào tập tin và chọn Delete thì:","level":1,"answer":[{"text":"Xóa tập tin vào thùng rác","isCorrect":true},{"text":"Xóa vĩnh viễn tập tin","isCorrect":false},{"text":"Xóa tập tin trong thùng rác","isCorrect":false},{"text":"Xoá tạm thời khi quay lại vẫn còn","isCorrect":false}],"score":0.0},{"question":"Trong một ổ đĩa thì tên một thư mục có thể:","level":1,"answer":[{"text":"Trùng với tên thư mục khác trong một ổ đĩa khác","isCorrect":false},{"text":"Trùng với phần tên của một tập tin trong cùng ổ đĩa","isCorrect":false},{"text":"Trùng với tên thư mục con","isCorrect":false},{"text":"Tất cả đáp án đều đúng","isCorrect":true}],"score":0.0},{"question":"Trong môi trường Windows bạn có thể chạy cùng lúc:","level":1,"answer":[{"text":"Chạy nhiều chương trình ứng dụng khác nhau","isCorrect":true},{"text":"Chỉ chạy được một chương trình","isCorrect":false},{"text":"Chỉ chạy được hai chương trình","isCorrect":false},{"text":"Chỉ chạy được ba chương trình","isCorrect":false}],"score":0.0},{"question":"Trong hệ điều hành Windows, muốn chọn tất cả các đối tượng trong một cửa sổ, ta sử dụng cách nào sau đây? ","level":1,"answer":[{"text":"Nhấn tổ hợp phím Ctrl + A","isCorrect":true},{"text":"Nhấn tổ hợp phím Ctrl + I","isCorrect":false},{"text":"Nhấn tổ hợp phím Alt + Tab","isCorrect":false},{"text":"Nhấn tổ hợp phím Ctrl + B","isCorrect":false}],"score":0.0},{"question":"Trong hệ điều hành Windows ta có thể mở:","level":1,"answer":[{"text":"Duy nhất một cửa sổ làm việc","isCorrect":false},{"text":"Nhiều cửa sổ làm việc cùng một lúc","isCorrect":true},{"text":"Tối đa bốn cửa sổ","isCorrect":false},{"text":"Chỉ cho phép mở từng cửa sổ","isCorrect":false}],"score":0.0},{"question":"Trong File Explorer, để đánh dấu chọn tất cả các đối tượng trong cửa sổ Folder hiện tại, ta nhấn phím:","level":1,"answer":[{"text":"F8","isCorrect":false},{"text":"F7","isCorrect":false},{"text":"Ctrl + A","isCorrect":true},{"text":"Ctrl + T","isCorrect":false}],"score":0.0},{"question":"Trên máy tính, mặc định để kích hoạt chương trình bằng một biểu tượng (icons) bằng chuột, ta phải thao tác:","level":1,"answer":[{"text":"Click chuột phải","isCorrect":false},{"text":"Nhấn Ctrl trước khi click chuột","isCorrect":false},{"text":"Click đôi chuột trái","isCorrect":true},{"text":"Click chuột trái","isCorrect":false}],"score":0.0},{"question":"Tổ hợp phím tắt Alt+Tab trong Windows dùng để:","level":1,"answer":[{"text":"Thoát cửa sổ hiện hành","isCorrect":false},{"text":"Phóng to cửa sổ hiện hành","isCorrect":false},{"text":"Chuyển đổi qua lại giữa các cửa sổ chương trình","isCorrect":true},{"text":"Thu nhỏ cửa sổ hiện hành xuống thanh Taskbar","isCorrect":false}],"score":0.0},{"question":"Tổ hợp phím Ctrl + Z dùng để:","level":1,"answer":[{"text":"Hủy thao tác","isCorrect":false},{"text":"Đóng cửa sổ đang mở","isCorrect":false},{"text":"Hủy kết quả của thao tác hoặc lệnh phía trước gần nhất kết quả hiện tại","isCorrect":true},{"text":"Đóng tập tin đang mở","isCorrect":false}],"score":0.0},{"question":"Thao tác nhấp chuột phải vào biểu tượng của thư mục/tập tin và chọn Properties là để:","level":1,"answer":[{"text":"Xem thuộc tính thư mục/tập tin","isCorrect":true},{"text":"Sao chép thư mục/tập tin","isCorrect":false},{"text":"Đổi tên thư mục/tập tin","isCorrect":false},{"text":"Xoá thư mục/tập tin","isCorrect":false}],"score":0.0},{"question":"Thao tác nhấp chuột phải vào biểu tượng của tệp tin và chọn Properties là để:","level":1,"answer":[{"text":"Xem thuộc tính tệp tin","isCorrect":true},{"text":"Sao chép tệp tin","isCorrect":false},{"text":"Xoá tệp tin","isCorrect":false},{"text":"Đổi tên tệp tin","isCorrect":false}],"score":0.0},{"question":"Thao tác nào cho phép xoá một thư mục hay một tệp tin đã được chọn:","level":1,"answer":[{"text":"Nhấp chuột phải và chọn Delete","isCorrect":false},{"text":"Bấm phím Delete","isCorrect":false},{"text":"Nhấn Shift + Delete","isCorrect":false},{"text":"Tất cả đáp án đều đúng","isCorrect":true}],"score":0.0},{"question":"Tệp tin có phần mở rộng là RAR, ZIP cho ta biết đây là:","level":1,"answer":[{"text":"File thực thi","isCorrect":false},{"text":"File video","isCorrect":false},{"text":"File nén","isCorrect":true},{"text":"File văn bản","isCorrect":false}],"score":0.0},{"question":"Phím, tổ hợp phím dùng để chụp màn hình","level":1,"answer":[{"text":"Ctrl+C","isCorrect":false},{"text":"Ctrl+Ins","isCorrect":false},{"text":"Print Screen","isCorrect":true},{"text":"ESC","isCorrect":false}],"score":0.0},{"question":"Phím, tổ hợp phím dùng để chụp cửa sổ hiện hành:","level":1,"answer":[{"text":"Alt+Print Screen","isCorrect":true},{"text":"Ctrl+Print Screen","isCorrect":false},{"text":"Print Screen","isCorrect":false},{"text":"Shift+ Print Screen","isCorrect":false}],"score":0.0},{"question":"Muốn xóa một chương trình trong Windows ta dùng cách nào sau đây","level":1,"answer":[{"text":"Xóa biểu tượng trên màn hình","isCorrect":false},{"text":"Vào Control panel chọn Devices and Printers","isCorrect":false},{"text":"Vào Control panel chọn Programs and Features","isCorrect":true},{"text":"Kéo biểu tượng vào thùng rác","isCorrect":false}],"score":0.0},{"question":"Muốn tạo một thư mục trên màn hình Desktop của Windows, ta kích chuột phải vào một chỗ trống trên Desktop và chọn:","level":1,"answer":[{"text":"Properties","isCorrect":false},{"text":"New - Folder","isCorrect":true},{"text":"New – Shortcut","isCorrect":false},{"text":"New – File","isCorrect":false}],"score":0.0},{"question":"Muốn tạo 1 thư mục mới trên ổ đĩa D: \\ trong Windows, ta đứng tại ổ đĩa D:\\ chọn:","level":1,"answer":[{"text":"Bấm chuột phải \\ New \\ Folder","isCorrect":true},{"text":"Bấm chuột phải \\ New \\ Shortcut","isCorrect":false},{"text":"Edit \\ New \\ Folder","isCorrect":false},{"text":"Insert \\ New \\ Folder","isCorrect":false}],"score":0.0},{"question":"Muốn sắp xếp các biểu tượng trên Desktop theo tên ta click phải. trên Desktop chọn sort by và chọn:","level":1,"answer":[{"text":"Name","isCorrect":true},{"text":"Size","isCorrect":false},{"text":"Item Type","isCorrect":false},{"text":"Date Modified","isCorrect":false}],"score":0.0},{"question":"Muốn khởi động chương trình File Explorer, người dùng có thể:","level":1,"answer":[{"text":"Nhấn tổ hợp phím Windows + E","isCorrect":false},{"text":"Nhấp chuột phải vào Start, chọn File Explorer","isCorrect":false},{"text":"Nhấp đúp chuột vào biểu tượng My Computer","isCorrect":false},{"text":"Tất cả đáp án đều đúng","isCorrect":true}],"score":0.0},{"question":"Muốn đóng cửa sổ của chương trình ta chọn:","level":1,"answer":[{"text":"Ctrl+X","isCorrect":false},{"text":"Edit \\ Exit","isCorrect":false},{"text":"Alt + F4","isCorrect":true},{"text":"Fn + F4","isCorrect":false}],"score":0.0},{"question":"Khi sử dụng mạng máy tính ta sẽ được các lợi ích:","level":1,"answer":[{"text":"Chia sẻ tài nguyên (ổ cứng, máy in, các phần mềm tiện ích,…)","isCorrect":false},{"text":"Quản lý tập trung","isCorrect":false},{"text":"Tận dụng năng lực xử lý của các máy tính rỗi để làm các đề án lớn","isCorrect":false},{"text":"Tất cả đáp án đều đúng","isCorrect":true}],"score":0.0},{"question":"File Explorer dùng để:","level":1,"answer":[{"text":"Quản lý tập tin","isCorrect":false},{"text":"Truy cập mạng","isCorrect":false},{"text":"Quản lý tập tin, thư mục","isCorrect":true},{"text":"Quản lý thư mục","isCorrect":false}],"score":0.0},{"question":"Để phòng chống Virus cách tốt nhất là:","level":1,"answer":[{"text":"Thường xuyên kiểm tra đĩa, đặc biệt thận trọng khi sao chép dữ liệu từ nơi khác mang tới","isCorrect":false},{"text":"Sử dụng các chương trình quét virus có bản quyền và cập nhật thường xuyên","isCorrect":false},{"text":"Không nên mở các mail có tệp lạ đính kèm","isCorrect":false},{"text":"Tất cả đáp án đều đúng","isCorrect":true}],"score":0.0},{"question":"Để mở cửa sổ cho phép bạn thêm một máy in:","level":1,"answer":[{"text":"Control Panel/Devices and Printer / Add a Printer","isCorrect":true},{"text":"Windows Explorer / Devices and Printer / Add a Printer","isCorrect":false},{"text":"Control Panel / Add and Remove Program / Add a Printer","isCorrect":false},{"text":"Control Panel / Add a Printer","isCorrect":false}],"score":0.0},{"question":"Để đóng một cửa sổ ứng dụng thực hiện:","level":1,"answer":[{"text":"Click nút Close trên thanh tiêu đề của cửa sổ trình ứng dụng","isCorrect":false},{"text":"Bấm tổ hợp phím Alt + F4","isCorrect":false},{"text":"Chọn menu Close của chương trình","isCorrect":false},{"text":"Tất cả đáp án đều đúng","isCorrect":true}],"score":0.0},{"question":"Để đổi tên một tập tin ta thực hiện:","level":1,"answer":[{"text":"Click chuột chọn đối tượng -> F2 -> Gõ tên mới -> Enter","isCorrect":true},{"text":"Click chuột phải vào đối tượng -> Create shortcut","isCorrect":false},{"text":"Click chuột phải vào đối tượng -> Open with","isCorrect":false},{"text":"Click chuột chọn đối tượng -> Gõ tên mới","isCorrect":false}],"score":0.0},{"question":"Đâu là phần mở rộng của tập tin cho biết đó là một bức ảnh:","level":1,"answer":[{"text":"Com","isCorrect":false},{"text":"Git","isCorrect":false},{"text":"M4a","isCorrect":false},{"text":"Jpg","isCorrect":true}],"score":0.0},{"question":"Đặc điểm chính của Virus máy tính là:","level":1,"answer":[{"text":"Phá hoại","isCorrect":false},{"text":"Lây lan","isCorrect":false},{"text":"Tự nhân bản","isCorrect":false},{"text":"Tất cả đáp án đều đúng","isCorrect":true}],"score":0.0},{"question":"Dùng chuột kéo và thả một File từ Folder này sang Folder khác trên cùng 1 ổ đĩa, đó là thao tác: ","level":1,"answer":[{"text":"Sao Chép","isCorrect":false},{"text":"Xoá","isCorrect":false},{"text":"Đổi Tên","isCorrect":false},{"text":"Di Chuyển","isCorrect":true}],"score":0.0},{"question":"Dùng chuột kéo và thả một File từ Folder này sang Folder khác đồng thời bấm giữ phím CTRL, đó là thao tác:","level":1,"answer":[{"text":"Xoá","isCorrect":false},{"text":"Di Chuyển","isCorrect":false},{"text":"Sao Chép","isCorrect":true},{"text":"Đổi Tên","isCorrect":false}],"score":0.0},{"question":"Control Panel dùng để:","level":1,"answer":[{"text":"Quản lý ổ đĩa","isCorrect":false},{"text":"Quản lý tập tin, thư mục","isCorrect":false},{"text":"Quản lý chương trình ứng dụng","isCorrect":false},{"text":"Quản lý, sửa đổi các thiết lập của Windows","isCorrect":true}],"score":0.0},{"question":"Các biểu tượng nào sau đây trên Desktop của hệ điều hành Windows được gọi là biểu tượng Shortcut? ","level":1,"answer":[{"text":"Recycle Bin","isCorrect":false},{"text":"Microsoft Word","isCorrect":true},{"text":"This PC","isCorrect":false},{"text":"Control Panel","isCorrect":false}],"score":0.0},{"question":"Bạn hiểu Virus tin học là gì?","level":1,"answer":[{"text":"Là một chương trình máy tính do con người tạo ra","isCorrect":false},{"text":"Có khả năng tự dấu kín, tự sao chép để lây lan","isCorrect":false},{"text":"Có khả năng phá hoại đối với các sản phẩm tin học","isCorrect":false},{"text":"Tất cả đáp án đều đúng","isCorrect":true}],"score":0.0}]